{"parent":"minecraft:item/generated","textures":{"layer0":"minecraft:item/iron_nugget"},"overrides":[{"predicate":{"custom_model_data":1},"model":"crown:podium/aqua_axolotls_podium"},{"predicate":{"custom_model_data":2},"model":"crown:podium/blue_bats_podium"},{"predicate":{"custom_model_data":3},"model":"crown:podium/cyan_coyotes_podium"},{"predicate":{"custom_model_data":4},"model":"crown:podium/green_geckos_podium"},{"predicate":{"custom_model_data":5},"model":"crown:podium/lime_llamas_podium"},{"predicate":{"custom_model_data":6},"model":"crown:podium/orange_ocelots_podium"},{"predicate":{"custom_model_data":7},"model":"crown:podium/pink_parrots_podium"},{"predicate":{"custom_model_data":8},"model":"crown:podium/purple_pandas_podium"},{"predicate":{"custom_model_data":9},"model":"crown:podium/red_rabbits_podium"},{"predicate":{"custom_model_data":10},"model":"crown:podium/yellow_yaks_podium"}]}